tahweel/__init__.py
tahweel/cli.py
tahweel/decorators/__init__.py
tahweel/decorators/retry.py
tahweel/enums/__init__.py
tahweel/enums/dir_output_type.py
tahweel/enums/output_format_type.py
tahweel/enums/tahweel_type.py
tahweel/enums/transformation_type.py
tahweel/managers/__init__.py
tahweel/managers/base_file_manager.py
tahweel/managers/file_managers_factory.py
tahweel/managers/image_file_manager.py
tahweel/managers/pdf_file_manager.py
tahweel/models/__init__.py
tahweel/models/transformation.py
tahweel/processors/__init__.py
tahweel/processors/base_ocr_processor.py
tahweel/processors/google_drive_base_ocr_processor.py
tahweel/processors/google_drive_ocr_processor.py
tahweel/processors/google_drive_on_colab_ocr_processor.py
tahweel/tahweel_argument_parser.py
tahweel/utils/__init__.py
tahweel/utils/image_utils.py
tahweel/utils/string_utils.py
tahweel/writers/__init__.py
tahweel/writers/docx_writer.py
tahweel/writers/txt_writer.py
tahweel-0.2.0.dist-info/LICENSE
tahweel-0.2.0.dist-info/METADATA
tahweel-0.2.0.dist-info/WHEEL
tahweel-0.2.0.dist-info/entry_points.txt
tahweel-0.2.0.dist-info/RECORD
