Metadata-Version: 2.3
Name: tahweel
Version: 0.2.0
Summary: تحويل ملفات PDF إلى Word و TXT
License: MIT
Keywords: tahweel,ocr,pdf,word,txt,google-drive-api
Author: EasyBooks
Author-email: easybooksdev@gmail.com
Requires-Python: >=3.10,<4.0
Classifier: Development Status :: 3 - Alpha
Classifier: Intended Audience :: Developers
Classifier: Intended Audience :: Education
Classifier: Intended Audience :: Science/Research
Classifier: License :: OSI Approved :: MIT License
Classifier: Operating System :: OS Independent
Classifier: Programming Language :: Python :: 3
Classifier: Programming Language :: Python :: 3.10
Classifier: Programming Language :: Python :: 3.11
Classifier: Programming Language :: Python :: 3.12
Classifier: Programming Language :: Python :: 3.13
Classifier: Topic :: Scientific/Engineering :: Artificial Intelligence
Requires-Dist: google-api-python-client (>=2.168.0,<3.0.0)
Requires-Dist: google-api-python-client-stubs (>=1.29.0,<2.0.0)
Requires-Dist: google-auth-oauthlib (>=1.2.2,<2.0.0)
Requires-Dist: pdf2image (>=1.17.0,<2.0.0)
Requires-Dist: pillow (>=11.2.1,<12.0.0)
Requires-Dist: platformdirs (>=4.3.7,<5.0.0)
Requires-Dist: python-docx (>=1.1.2,<2.0.0)
Requires-Dist: tqdm (>=4.67.1,<5.0.0)
Requires-Dist: typed-argument-parser (>=1.10.1,<2.0.0)
Requires-Dist: types-tqdm (>=4.67.0.20250417,<5.0.0.0)
Project-URL: Homepage, https://tahweel.ieasybooks.com
Project-URL: Repository, https://github.com/ieasybooks/tahweel
